mcp_data_analyzer/__init__.py
mcp_data_analyzer/__main__.py
mcp_data_analyzer/cli.py
mcp_data_analyzer/core.py
anxinxin_mcp_data_analzyer-0.1.2.dist-info/METADATA
anxinxin_mcp_data_analzyer-0.1.2.dist-info/WHEEL
anxinxin_mcp_data_analzyer-0.1.2.dist-info/entry_points.txt
anxinxin_mcp_data_analzyer-0.1.2.dist-info/top_level.txt
anxinxin_mcp_data_analzyer-0.1.2.dist-info/RECORD
