Metadata-Version: 2.4
Name: AnXinxin-mcp-data-analzyer
Version: 0.1.2
Summary: a mcp-data-analzyer mcp server
Requires-Python: >=3.11
Requires-Dist: matplotlib>=3.10.8
Requires-Dist: mcp[cli]>=1.25.0
Requires-Dist: openpyxl>=3.1.5
Requires-Dist: pandas>=2.3.3
Requires-Dist: twine>=6.2.0
